elabapy_cli/__init__.py
elabapy_cli/globals.py
elabapy_cli/main.py
elabapy_cli/version.py
elabapy_cli/cli/__init__.py
elabapy_cli/cli/backups.py
elabapy_cli/cli/config.py
elabapy_cli/cli/decorator.py
elabapy_cli/cli/events.py
elabapy_cli/cli/experiments.py
elabapy_cli/cli/items.py
elabapy_cli/lib/__init__.py
elabapy_cli/lib/climanager.py
elabapy_cli-0.4.1.dist-info/LICENSE
elabapy_cli-0.4.1.dist-info/METADATA
elabapy_cli-0.4.1.dist-info/WHEEL
elabapy_cli-0.4.1.dist-info/entry_points.txt
elabapy_cli-0.4.1.dist-info/top_level.txt
elabapy_cli-0.4.1.dist-info/RECORD
