Metadata-Version: 2.1
Name: elabapy-cli
Version: 0.4.1
Summary: eLabFTW CLI library.
Home-page: https://gitlab.com/iam-cms/workflows/extra-nodes/elabapy-cli
Author: Karlsruhe Institute of Technology
License: GNU GPL-3.0
Platform: UNKNOWN
Classifier: Development Status :: 4 - Beta
Classifier: License :: OSI Approved :: GNU General Public License v3 (GPLv3)
Classifier: Operating System :: OS Independent
Classifier: Programming Language :: Python :: 3
Requires-Python: >=3.6
Requires-Dist: Click (<8.0.0,>=7.1.1)
Requires-Dist: click-completion (>=0.5.2)
Requires-Dist: requests (>=2.22.0)
Requires-Dist: xmlhelpy (>=0.2.0)
Requires-Dist: elabapy (>=0.7.0)
Provides-Extra: dev
Requires-Dist: black (==20.8b1) ; extra == 'dev'
Requires-Dist: pre-commit (>=2.7.0) ; extra == 'dev'
Requires-Dist: pylint (<2.5.0,>=2.4.4) ; extra == 'dev'
Requires-Dist: tox (>=3.15.0) ; extra == 'dev'
